{"n":100,"ayahs":[{"n":1,"g":6147,"t":"بِسْمِ ٱللَّهِ ٱلرَّحْمَٰنِ ٱلرَّحِيمِ وَٱلْعَٰدِيَٰتِ ضَبْحًۭا","tf":"أقسم الله تعالى بالخيل الجاريات في سبيله نحو العدوِّ، حين يظهر صوتها من سرعة عَدْوِها. ولا يجوز للمخلوق أن يقسم إلا بالله، فإن القسم بغير الله شرك.","j":30,"p":599},{"n":2,"g":6148,"t":"فَٱلْمُورِيَٰتِ قَدْحًۭا","tf":"فالخيل اللاتي تنقدح النار من صلابة حوافرها؛ من شدَّة عَدْوها.","j":30,"p":599},{"n":3,"g":6149,"t":"فَٱلْمُغِيرَٰتِ صُبْحًۭا","tf":"فالمغيرات على الأعداء عند الصبح.","j":30,"p":599},{"n":4,"g":6150,"t":"فَأَثَرْنَ بِهِۦ نَقْعًۭا","tf":"فهيَّجْنَ بهذا العَدْو غبارًا.","j":30,"p":599},{"n":5,"g":6151,"t":"فَوَسَطْنَ بِهِۦ جَمْعًا","tf":"فتوسَّطن بركبانهن جموع الأعداء.","j":30,"p":599},{"n":6,"g":6152,"t":"إِنَّ ٱلْإِنسَٰنَ لِرَبِّهِۦ لَكَنُودٌۭ","tf":"إن الإنسان لِنعم ربه لَجحود، وإنه بجحوده ذلك لمقر. وإنه لحب المال لشديد.","j":30,"p":599},{"n":7,"g":6153,"t":"وَإِنَّهُۥ عَلَىٰ ذَٰلِكَ لَشَهِيدٌۭ","tf":"إن الإنسان لِنعم ربه لَجحود، وإنه بجحوده ذلك لمقر. وإنه لحب المال لشديد.","j":30,"p":599},{"n":8,"g":6154,"t":"وَإِنَّهُۥ لِحُبِّ ٱلْخَيْرِ لَشَدِيدٌ","tf":"إن الإنسان لِنعم ربه لَجحود، وإنه بجحوده ذلك لمقر. وإنه لحب المال لشديد.","j":30,"p":599},{"n":9,"g":6155,"t":"۞ أَفَلَا يَعْلَمُ إِذَا بُعْثِرَ مَا فِى ٱلْقُبُورِ","tf":"أفلا يعلم الإنسان ما ينتظره إذا أخرج الله الأموات من القبور للحساب والجزاء؟","j":30,"p":599},{"n":10,"g":6156,"t":"وَحُصِّلَ مَا فِى ٱلصُّدُورِ","tf":"واستُخرج ما استتر في الصدور من خير أو شر.","j":30,"p":600},{"n":11,"g":6157,"t":"إِنَّ رَبَّهُم بِهِمْ يَوْمَئِذٍۢ لَّخَبِيرٌۢ","tf":"إن ربهم بهم وبأعمالهم يومئذ لخبير، لا يخفى عليه شيء من ذلك.","j":30,"p":600}]}